odoo/addons/account_invoice_fix_tax_rounding/README.rst
odoo/addons/account_invoice_fix_tax_rounding/__init__.py
odoo/addons/account_invoice_fix_tax_rounding/__manifest__.py
odoo/addons/account_invoice_fix_tax_rounding/i18n/account_invoice_fix_tax_rounding.pot
odoo/addons/account_invoice_fix_tax_rounding/i18n/es.po
odoo/addons/account_invoice_fix_tax_rounding/i18n/it.po
odoo/addons/account_invoice_fix_tax_rounding/i18n/pt_BR.po
odoo/addons/account_invoice_fix_tax_rounding/models/__init__.py
odoo/addons/account_invoice_fix_tax_rounding/models/account_invoice.py
odoo/addons/account_invoice_fix_tax_rounding/models/res_company.py
odoo/addons/account_invoice_fix_tax_rounding/models/res_config_settings.py
odoo/addons/account_invoice_fix_tax_rounding/readme/CONFIGURE.rst
odoo/addons/account_invoice_fix_tax_rounding/readme/CONTRIBUTORS.rst
odoo/addons/account_invoice_fix_tax_rounding/readme/DESCRIPTION.rst
odoo/addons/account_invoice_fix_tax_rounding/static/description/icon.png
odoo/addons/account_invoice_fix_tax_rounding/static/description/index.html
odoo/addons/account_invoice_fix_tax_rounding/views/res_config_settings_views.xml
odoo12_addon_account_invoice_fix_tax_rounding-12.0.1.0.0.99.dev11.dist-info/METADATA
odoo12_addon_account_invoice_fix_tax_rounding-12.0.1.0.0.99.dev11.dist-info/WHEEL
odoo12_addon_account_invoice_fix_tax_rounding-12.0.1.0.0.99.dev11.dist-info/top_level.txt
odoo12_addon_account_invoice_fix_tax_rounding-12.0.1.0.0.99.dev11.dist-info/RECORD
